wdecipher/__init__.py
wdecipher/wx_db.py
wdecipher/wx_info.py
wdecipher/utils/__init__.py
wdecipher/utils/sqlite.py
wdecipher/utils/win32_process.py
wdecipher-0.0.1.dist-info/LICENSE
wdecipher-0.0.1.dist-info/METADATA
wdecipher-0.0.1.dist-info/WHEEL
wdecipher-0.0.1.dist-info/top_level.txt
wdecipher-0.0.1.dist-info/zip-safe
wdecipher-0.0.1.dist-info/RECORD
