Metadata-Version: 2.1
Name: wdecipher
Version: 0.0.1
Summary: WDecipher is a third-party extension tool for WeChat that can decrypt WeChat SQLite databases and export and merge databases.
Home-page: https://github.com/gndlwch2w/wdecipher
Author: Chisheng Chen
Author-email: chishengchen@126.com
License: MIT-0
Requires-Python: >=3.6
License-File: LICENSE
Requires-Dist: setuptools
Requires-Dist: pycryptodomex
